{
  "$schema": "https://ui.shadcn.com/schema/registry-item.json",
  "name": "oui-input",
  "type": "registry:ui",
  "title": "Input",
  "description": "React aria components Input with shadcn characteristics.",
  "dependencies": [
    "react-aria-components",
    "class-variance-authority",
    "tailwind-merge"
  ],
  "registryDependencies": [
    "@oui/oui-base"
  ],
  "files": [
    {
      "path": "registry/default/ui/oui-input.tsx",
      "content": "\"use client\";\n\nimport * as React from \"react\";\nimport {\n  composeTailwindRenderProps,\n  focusVisibleStyles,\n} from \"@/registry/default/ui/oui-base\";\nimport * as Rac from \"react-aria-components\";\nimport { twJoin } from \"tailwind-merge\";\n\nexport const inputStyles = twJoin(\n  focusVisibleStyles,\n  \"h-9 w-full min-w-0 rounded-md border border-input bg-transparent px-3 py-1 text-base shadow-xs transition-[color,box-shadow] outline-none placeholder:text-muted-foreground md:text-sm dark:bg-input/30\",\n  \"file:inline-flex file:h-7 file:border-0 file:bg-transparent file:text-sm file:font-medium file:text-foreground\",\n  \"selection:bg-primary selection:text-primary-foreground\",\n  \"data-disabled:pointer-events-none data-disabled:cursor-not-allowed data-disabled:opacity-50\",\n  \"data-invalid:border-destructive data-invalid:ring-destructive/20 dark:data-invalid:ring-destructive/40\",\n  \"[&::-webkit-search-cancel-button]:hidden\",\n);\n\n/**\n * Derived from shadcn Input.\n */\nexport function Input({\n  className,\n  ...props\n}: React.ComponentProps<typeof Rac.Input>) {\n  return (\n    <Rac.Input\n      data-slot=\"input\"\n      className={composeTailwindRenderProps(className, inputStyles)}\n      {...props}\n    />\n  );\n}\n",
      "type": "registry:ui"
    }
  ],
  "meta": {
    "tags": [
      "input"
    ]
  }
}